{
    "meta": {
        "song_id": "00000428",
        "dataset": "DAMP",
        "title": "Happy End",
        "artist": "Пара Нормальных",
        "language": "ru",
        "writer_artirsts": [
            "Иван Дорн (Ivan Dorn)"
        ]
    },
    "annotations": [
        {
            "paragraph": "Verse",
            "occurrence": 1,
            "time_index": [
                15.210416666666667,
                38.760416666666664
            ],
            "time_duration": 23.549999999999997,
            "singer": [
                "Иван Дорн"
            ],
            "lines": [
                {
                    "line": "Нарисую мелом, напишу:",
                    "time_index": [
                        15.210416666666667,
                        18.4
                    ],
                    "time_duration": 3.1895833333333314
                },
                {
                    "line": "«I love you».",
                    "time_index": [
                        18.5,
                        21.65
                    ],
                    "time_duration": 3.1499999999999986
                },
                {
                    "line": "Два сценария одной судьбы,",
                    "time_index": [
                        21.75,
                        25.169791666666665
                    ],
                    "time_duration": 3.419791666666665
                },
                {
                    "line": "Разный взгляд и цвет одной игры.",
                    "time_index": [
                        25.269791666666666,
                        25.169791666666665
                    ],
                    "time_duration": -0.10000000000000142
                },
                {
                    "line": "",
                    "time_index": [
                        25.269791666666666,
                        28.419791666666665
                    ],
                    "time_duration": 3.1499999999999986
                },
                {
                    "line": "Напишу о том, что ты ушла,",
                    "time_index": [
                        28.519791666666666,
                        31.93958333333333
                    ],
                    "time_duration": 3.419791666666665
                },
                {
                    "line": "Но вернулась вскоре навсегда.",
                    "time_index": [
                        32.03958333333333,
                        35.21041666666667
                    ],
                    "time_duration": 3.1708333333333343
                },
                {
                    "line": "Ты же рисовала на открытках",
                    "time_index": [
                        35.31041666666667,
                        38.760416666666664
                    ],
                    "time_duration": 3.4499999999999957
                },
                {
                    "line": "Двери для меня, что впредь закрыты.",
                    "time_index": [
                        38.860416666666666,
                        38.760416666666664
                    ],
                    "time_duration": -0.10000000000000142
                },
                {
                    "line": "",
                    "time_index": [
                        38.860416666666666,
                        43.53958333333333
                    ],
                    "time_duration": 4.679166666666667
                },
                {
                    "line": "Не пиши «The end», я придумаю Happy end.",
                    "time_index": [
                        43.639583333333334,
                        50.06041666666666
                    ],
                    "time_duration": 6.420833333333327
                },
                {
                    "line": "Поверну всё так, чтоб два",
                    "time_index": [
                        50.16041666666666,
                        53.81979166666667
                    ],
                    "time_duration": 3.6593750000000043
                },
                {
                    "line": "сердца вновь бились в такт.",
                    "time_index": [
                        53.91979166666667,
                        56.83958333333333
                    ],
                    "time_duration": 2.9197916666666615
                },
                {
                    "line": "Всё ведь как в кино,",
                    "time_index": [
                        56.93958333333333,
                        60.599999999999994
                    ],
                    "time_duration": 3.660416666666663
                },
                {
                    "line": "разреши лишь доснять его.",
                    "time_index": [
                        60.699999999999996,
                        63.63020833333333
                    ],
                    "time_duration": 2.930208333333333
                },
                {
                    "line": "Не пиши «The end», я придумаю Happy end.",
                    "time_index": [
                        63.73020833333333,
                        63.63020833333333
                    ],
                    "time_duration": -0.10000000000000142
                },
                {
                    "line": "",
                    "time_index": [
                        63.73020833333333,
                        74.38020833333334
                    ],
                    "time_duration": 10.650000000000013
                },
                {
                    "line": "Ты же знаешь всё исправить можно,",
                    "time_index": [
                        74.48020833333334,
                        77.63020833333334
                    ],
                    "time_duration": 3.1500000000000057
                },
                {
                    "line": "Зачеркнуть, переписать обложку,",
                    "time_index": [
                        77.73020833333334,
                        80.9
                    ],
                    "time_duration": 3.1697916666666686
                },
                {
                    "line": "Переснять все сцены, монологи",
                    "time_index": [
                        81.0,
                        84.16979166666667
                    ],
                    "time_duration": 3.1697916666666686
                },
                {
                    "line": "Из сюжетов вычеркнуть так много…",
                    "time_index": [
                        84.26979166666666,
                        84.16979166666667
                    ],
                    "time_duration": -0.09999999999999432
                },
                {
                    "line": "",
                    "time_index": [
                        84.26979166666666,
                        87.71041666666667
                    ],
                    "time_duration": 3.4406250000000114
                },
                {
                    "line": "Декорации сменить на осень",
                    "time_index": [
                        87.81041666666667,
                        91.21979166666667
                    ],
                    "time_duration": 3.409374999999997
                },
                {
                    "line": "О локациях никто не спросит.",
                    "time_index": [
                        91.31979166666666,
                        94.46979166666667
                    ],
                    "time_duration": 3.1500000000000057
                },
                {
                    "line": "Разреши мне сделать это тайно,",
                    "time_index": [
                        94.56979166666666,
                        97.71979166666667
                    ],
                    "time_duration": 3.1500000000000057
                },
                {
                    "line": "Чтоб все получилось, как случайно.",
                    "time_index": [
                        97.81979166666666,
                        97.71979166666667
                    ],
                    "time_duration": -0.09999999999999432
                },
                {
                    "line": "",
                    "time_index": [
                        97.81979166666666,
                        102.5
                    ],
                    "time_duration": 4.68020833333334
                },
                {
                    "line": "Не пиши «The end», я придумаю Happy end",
                    "time_index": [
                        102.6,
                        109.03958333333334
                    ],
                    "time_duration": 6.439583333333346
                },
                {
                    "line": "Поверну всё так, чтоб два",
                    "time_index": [
                        109.13958333333333,
                        113.03958333333334
                    ],
                    "time_duration": 3.9000000000000057
                },
                {
                    "line": "сердца вновь бились в такт.",
                    "time_index": [
                        113.13958333333333,
                        116.06979166666667
                    ],
                    "time_duration": 2.93020833333334
                },
                {
                    "line": "Всё ведь как в кино,",
                    "time_index": [
                        116.16979166666667,
                        119.83020833333333
                    ],
                    "time_duration": 3.660416666666663
                },
                {
                    "line": "разреши лишь доснять его.",
                    "time_index": [
                        119.93020833333333,
                        122.83020833333333
                    ],
                    "time_duration": 2.9000000000000057
                },
                {
                    "line": "Не пиши «The end», я придумаю Happy end",
                    "time_index": [
                        122.93020833333333,
                        122.83020833333333
                    ],
                    "time_duration": -0.09999999999999432
                },
                {
                    "line": "",
                    "time_index": [
                        122.93020833333333,
                        160.01041666666666
                    ],
                    "time_duration": 37.08020833333333
                },
                {
                    "line": "Не пиши «The end», я придумаю Happy end",
                    "time_index": [
                        160.11041666666665,
                        166.6
                    ],
                    "time_duration": 6.489583333333343
                },
                {
                    "line": "Поверну всё так, чтоб два",
                    "time_index": [
                        166.7,
                        170.83958333333334
                    ],
                    "time_duration": 4.1395833333333485
                },
                {
                    "line": "сердца вновь бились в такт.",
                    "time_index": [
                        170.93958333333333,
                        173.36041666666668
                    ],
                    "time_duration": 2.4208333333333485
                },
                {
                    "line": "Всё ведь как в кино,",
                    "time_index": [
                        173.46041666666667,
                        177.11979166666666
                    ],
                    "time_duration": 3.659374999999983
                },
                {
                    "line": "разреши лишь доснять его.",
                    "time_index": [
                        177.21979166666665,
                        180.13020833333334
                    ],
                    "time_duration": 2.9104166666666913
                },
                {
                    "line": "Не пиши «The end», я придумаю Happy end",
                    "time_index": [
                        180.23020833333334,
                        216.12
                    ],
                    "time_duration": 35.88979166666667
                }
            ]
        }
    ]
}