{
    "meta": {
        "song_id": "000001D5",
        "dataset": "DAMP",
        "title": "Vencer al amor",
        "artist": "India Martinez",
        "language": "es",
        "writer_artirsts": [
            "India Martínez"
        ]
    },
    "annotations": [
        {
            "paragraph": "Verse",
            "occurrence": 1,
            "time_index": [
                19.460416666666667,
                280.706
            ],
            "time_duration": 183.33958333333334,
            "singer": [
                "India Martinez"
            ],
            "lines": [
                {
                    "line": "Cuantas veces te llamaba",
                    "time_index": [
                        19.460416666666667,
                        22.410416666666666
                    ],
                    "time_duration": 2.9499999999999993
                },
                {
                    "line": "te llamaba sola y triste",
                    "time_index": [
                        22.510416666666668,
                        24.680208333333333
                    ],
                    "time_duration": 2.169791666666665
                },
                {
                    "line": "pero nunca estabas, nunca estabas,",
                    "time_index": [
                        24.780208333333334,
                        28.960416666666664
                    ],
                    "time_duration": 4.180208333333329
                },
                {
                    "line": "y perdi..",
                    "time_index": [
                        29.060416666666665,
                        33.23020833333333
                    ],
                    "time_duration": 4.169791666666665
                },
                {
                    "line": "Perdi la voz, mi corazón,",
                    "time_index": [
                        33.33020833333333,
                        35.75
                    ],
                    "time_duration": 2.4197916666666686
                },
                {
                    "line": "se fue arrugando en",
                    "time_index": [
                        35.85,
                        37.01979166666666
                    ],
                    "time_duration": 1.1697916666666615
                },
                {
                    "line": "un rincon de miedo",
                    "time_index": [
                        37.119791666666664,
                        39.530208333333334
                    ],
                    "time_duration": 2.41041666666667
                },
                {
                    "line": "y solo hay una vida vida vida",
                    "time_index": [
                        39.630208333333336,
                        42.56979166666667
                    ],
                    "time_duration": 2.9395833333333314
                },
                {
                    "line": "por vivir.",
                    "time_index": [
                        42.66979166666667,
                        42.56979166666667
                    ],
                    "time_duration": -0.10000000000000142
                },
                {
                    "line": "",
                    "time_index": [
                        42.66979166666667,
                        46.13020833333333
                    ],
                    "time_duration": 3.46041666666666
                },
                {
                    "line": "Camino y camino pero no",
                    "time_index": [
                        46.23020833333333,
                        49.199999999999996
                    ],
                    "time_duration": 2.9697916666666657
                },
                {
                    "line": "levanto el vuelo,",
                    "time_index": [
                        49.3,
                        52.75
                    ],
                    "time_duration": 3.450000000000003
                },
                {
                    "line": "levanto un castillo de ilusiones y",
                    "time_index": [
                        52.85,
                        57.030208333333334
                    ],
                    "time_duration": 4.180208333333333
                },
                {
                    "line": "sueños con mis manos sola en",
                    "time_index": [
                        57.130208333333336,
                        59.03958333333333
                    ],
                    "time_duration": 1.9093749999999972
                },
                {
                    "line": "mi silencio",
                    "time_index": [
                        59.139583333333334,
                        61.05
                    ],
                    "time_duration": 1.9104166666666629
                },
                {
                    "line": "Y volar...",
                    "time_index": [
                        61.15,
                        64.06979166666667
                    ],
                    "time_duration": 2.9197916666666757
                },
                {
                    "line": "y acariciar el cielo",
                    "time_index": [
                        64.16979166666667,
                        65.60000000000001
                    ],
                    "time_duration": 1.43020833333334
                },
                {
                    "line": "con mis manos y olvidar mi dolor,",
                    "time_index": [
                        65.7,
                        74.18958333333333
                    ],
                    "time_duration": 8.489583333333329
                },
                {
                    "line": "inventar horizontes nuevos.",
                    "time_index": [
                        74.28958333333333,
                        80.48020833333334
                    ],
                    "time_duration": 6.190625000000011
                },
                {
                    "line": "Y cantar...",
                    "time_index": [
                        80.58020833333333,
                        84.26979166666668
                    ],
                    "time_duration": 3.6895833333333456
                },
                {
                    "line": "hasta romper mi voz gritando",
                    "time_index": [
                        84.36979166666667,
                        87.28958333333334
                    ],
                    "time_duration": 2.9197916666666686
                },
                {
                    "line": "y vencer al amor...",
                    "time_index": [
                        87.38958333333333,
                        94.08958333333334
                    ],
                    "time_duration": 6.700000000000003
                },
                {
                    "line": "y vencer al amor...",
                    "time_index": [
                        94.18958333333333,
                        94.08958333333334
                    ],
                    "time_duration": -0.09999999999999432
                },
                {
                    "line": "",
                    "time_index": [
                        94.18958333333333,
                        114.71041666666667
                    ],
                    "time_duration": 20.520833333333343
                },
                {
                    "line": "Una razon 4 besos y un",
                    "time_index": [
                        114.81041666666667,
                        116.76979166666668
                    ],
                    "time_duration": 1.9593750000000085
                },
                {
                    "line": "portazo y un te quiero que me",
                    "time_index": [
                        116.86979166666667,
                        119.28020833333333
                    ],
                    "time_duration": 2.410416666666663
                },
                {
                    "line": "esta matando,",
                    "time_index": [
                        119.38020833333333,
                        122.03958333333334
                    ],
                    "time_duration": 2.6593750000000114
                },
                {
                    "line": "me esta matando y me puede",
                    "time_index": [
                        122.13958333333333,
                        127.83020833333333
                    ],
                    "time_duration": 5.690624999999997
                },
                {
                    "line": "quiero salir",
                    "time_index": [
                        127.93020833333333,
                        134.35
                    ],
                    "time_duration": 6.419791666666669
                },
                {
                    "line": "abriré por fin mis alas blancas...",
                    "time_index": [
                        134.45,
                        134.35
                    ],
                    "time_duration": -0.09999999999999432
                },
                {
                    "line": "",
                    "time_index": [
                        134.45,
                        140.66979166666667
                    ],
                    "time_duration": 6.21979166666668
                },
                {
                    "line": "Camino y camino pero no",
                    "time_index": [
                        140.76979166666666,
                        144.18958333333333
                    ],
                    "time_duration": 3.4197916666666686
                },
                {
                    "line": "levanto el vuelo,",
                    "time_index": [
                        144.28958333333333,
                        147.51979166666666
                    ],
                    "time_duration": 3.230208333333337
                },
                {
                    "line": "levanto un castillo de ilusiones",
                    "time_index": [
                        147.61979166666666,
                        152.56041666666667
                    ],
                    "time_duration": 4.940625000000011
                },
                {
                    "line": "y sueños..",
                    "time_index": [
                        152.66041666666666,
                        154.33958333333334
                    ],
                    "time_duration": 1.6791666666666742
                },
                {
                    "line": "Camino y camino pero no",
                    "time_index": [
                        154.43958333333333,
                        157.61979166666666
                    ],
                    "time_duration": 3.1802083333333258
                },
                {
                    "line": "levanto el vuelo,",
                    "time_index": [
                        157.71979166666665,
                        160.9
                    ],
                    "time_duration": 3.180208333333354
                },
                {
                    "line": "levanto un castillo de ilusiones",
                    "time_index": [
                        161.0,
                        167.21979166666668
                    ],
                    "time_duration": 6.21979166666668
                },
                {
                    "line": "y sueños",
                    "time_index": [
                        167.31979166666667,
                        169.01979166666666
                    ],
                    "time_duration": 1.6999999999999886
                },
                {
                    "line": "Y volar y acariciar el",
                    "time_index": [
                        169.11979166666666,
                        173.33020833333333
                    ],
                    "time_duration": 4.210416666666674
                },
                {
                    "line": "cielo con mis manos,",
                    "time_index": [
                        173.43020833333333,
                        175.6
                    ],
                    "time_duration": 2.1697916666666686
                },
                {
                    "line": "y olvidar mi dolor…",
                    "time_index": [
                        175.7,
                        182.38958333333335
                    ],
                    "time_duration": 6.68958333333336
                },
                {
                    "line": "inventar horizontes nuevos.",
                    "time_index": [
                        182.48958333333334,
                        188.68958333333333
                    ],
                    "time_duration": 6.199999999999989
                },
                {
                    "line": "Y cantar y hasta romper",
                    "time_index": [
                        188.78958333333333,
                        193.96979166666668
                    ],
                    "time_duration": 5.180208333333354
                },
                {
                    "line": "mi voz gritando y vencer",
                    "time_index": [
                        194.06979166666667,
                        198.76041666666666
                    ],
                    "time_duration": 4.690624999999983
                },
                {
                    "line": "al amor…",
                    "time_index": [
                        198.86041666666665,
                        202.8
                    ],
                    "time_duration": 3.93958333333336
                },
                {
                    "line": "al amor… ay",
                    "time_index": [
                        202.9,
                        202.8
                    ],
                    "time_duration": -0.09999999999999432
                },
                {
                    "line": "",
                    "time_index": [
                        202.9,
                        215.13958333333335
                    ],
                    "time_duration": 12.239583333333343
                },
                {
                    "line": "Cuantas veces te llamaba,",
                    "time_index": [
                        215.23958333333334,
                        216.66979166666667
                    ],
                    "time_duration": 1.4302083333333258
                },
                {
                    "line": "te llamaba sola y triste..",
                    "time_index": [
                        216.76979166666666,
                        218.96041666666667
                    ],
                    "time_duration": 2.1906250000000114
                },
                {
                    "line": "pero nunca estabas…",
                    "time_index": [
                        219.06041666666667,
                        280.706
                    ],
                    "time_duration": 61.64558333333335
                }
            ]
        }
    ]
}