{
    "meta": {
        "song_id": "000008DB",
        "title": "Ol' 55",
        "artist": "Tom Waits",
        "language": "en"
    },
    "annotations": [
        {
            "paragraph": "Verse",
            "occurrence": 1,
            "time_index": [
                17.90276,
                43.6320954943274
            ],
            "time_duration": 25.7293354943274,
            "singer": [
                "Tom Waits"
            ],
            "lines": [
                {
                    "line": "well my time went so quickly,",
                    "time_index": [
                        17.90276,
                        21.346844278768234
                    ],
                    "time_duration": 3.4440842787682335
                },
                {
                    "line": "i went lickety-splickly",
                    "time_index": [
                        21.498789173419773,
                        24.183148978930312
                    ],
                    "time_duration": 2.684359805510539
                },
                {
                    "line": "out to my old 'fifty fife",
                    "time_index": [
                        25.803894521880068,
                        29.551868589951383
                    ],
                    "time_duration": 3.747974068071315
                },
                {
                    "line": "as i pulled away slowly,",
                    "time_index": [
                        31.729745413290118,
                        35.02188479740681
                    ],
                    "time_duration": 3.2921393841166946
                },
                {
                    "line": "feeling so holy,",
                    "time_index": [
                        36.03485076175041,
                        38.46596907617505
                    ],
                    "time_duration": 2.431118314424637
                },
                {
                    "line": "god knows,",
                    "time_index": [
                        38.61791397082659,
                        39.93476972447327
                    ],
                    "time_duration": 1.3168557536466778
                },
                {
                    "line": "i was feeling alive.",
                    "time_index": [
                        40.441252706645066,
                        43.6320954943274
                    ],
                    "time_duration": 3.1908427876823353
                }
            ]
        },
        {
            "paragraph": "Chorus",
            "occurrence": 1,
            "time_index": [
                45.30348933549433,
                90.58306794165318
            ],
            "time_duration": 45.27957860615885,
            "singer": [
                "Tom Waits"
            ],
            "lines": [
                {
                    "line": "now the suns coming up,",
                    "time_index": [
                        45.30348933549433,
                        49.811187876823354
                    ],
                    "time_duration": 4.50769854132902
                },
                {
                    "line": "i'm riding with lady luck,",
                    "time_index": [
                        52.596844278768245,
                        56.39546664505674
                    ],
                    "time_duration": 3.798622366288498
                },
                {
                    "line": "freeway cars and trucks,",
                    "time_index": [
                        59.48501283630472,
                        63.08104200972449
                    ],
                    "time_duration": 3.5960291734197725
                },
                {
                    "line": "stars beginning to fade,",
                    "time_index": [
                        66.87966437601298,
                        69.96921056726096
                    ],
                    "time_duration": 3.089546191247976
                },
                {
                    "line": "and i lead the parade",
                    "time_index": [
                        73.362646547812,
                        76.30024784440846
                    ],
                    "time_duration": 2.937601296596455
                },
                {
                    "line": "just a-wishing",
                    "time_index": [
                        79.84562871961104,
                        81.41572596434362
                    ],
                    "time_duration": 1.5700972447325796
                },
                {
                    "line": "i'd stayed a little longer,",
                    "time_index": [
                        81.51702256077797,
                        84.65721705024313
                    ],
                    "time_duration": 3.1401944894651592
                },
                {
                    "line": "oh, lord,",
                    "time_index": [
                        86.37925918962725,
                        87.34157685575367
                    ],
                    "time_duration": 0.9623176661264239
                },
                {
                    "line": "let me tell you that the",
                    "time_index": [
                        87.69611494327393,
                        88.40519111831445
                    ],
                    "time_duration": 0.7090761750405221
                },
                {
                    "line": "feelings getting stronger.",
                    "time_index": [
                        88.60778431118317,
                        90.58306794165318
                    ],
                    "time_duration": 1.9752836304700168
                }
            ]
        },
        {
            "paragraph": "Verse",
            "occurrence": 2,
            "time_index": [
                94.43233860615886,
                119.0474115397083
            ],
            "time_duration": 24.615072933549442,
            "singer": [
                "Tom Waits"
            ],
            "lines": [
                {
                    "line": "and it's six in the morning,",
                    "time_index": [
                        94.43233860615886,
                        97.57253309562402
                    ],
                    "time_duration": 3.1401944894651592
                },
                {
                    "line": "gave me no warning;",
                    "time_index": [
                        98.53485076175043,
                        100.91532077795789
                    ],
                    "time_duration": 2.380470016207454
                },
                {
                    "line": "i had to be on my way.",
                    "time_index": [
                        101.06726567260944,
                        105.27107442463536
                    ],
                    "time_duration": 4.203808752025921
                },
                {
                    "line": "well theres trucks all a-passing me,",
                    "time_index": [
                        107.49959954619128,
                        110.79173893030797
                    ],
                    "time_duration": 3.2921393841166946
                },
                {
                    "line": "and the lights all are flashing,",
                    "time_index": [
                        110.79173893030797,
                        113.7799885251216
                    ],
                    "time_duration": 2.988249594813624
                },
                {
                    "line": "i'm on my way home from your place.",
                    "time_index": [
                        114.38776810372775,
                        119.0474115397083
                    ],
                    "time_duration": 4.659643435980556
                }
            ]
        },
        {
            "paragraph": "Chorus",
            "occurrence": 2,
            "time_index": [
                120.21232239870345,
                165.54254930307948
            ],
            "time_duration": 45.33022690437603,
            "singer": [
                "Tom Waits"
            ],
            "lines": [
                {
                    "line": "and now the suns coming up,",
                    "time_index": [
                        120.21232239870345,
                        124.82131753646682
                    ],
                    "time_duration": 4.608995137763372
                },
                {
                    "line": "i'm riding with lady luck,",
                    "time_index": [
                        127.404380745543,
                        131.1523548136143
                    ],
                    "time_duration": 3.7479740680713007
                },
                {
                    "line": "freeway cars and trucks",
                    "time_index": [
                        134.14060440842792,
                        137.78728188006488
                    ],
                    "time_duration": 3.6466774716369628
                },
                {
                    "line": "stars beginning to fade,",
                    "time_index": [
                        141.58590424635338,
                        144.82739533225288
                    ],
                    "time_duration": 3.241491085899497
                },
                {
                    "line": "and i lead the parade",
                    "time_index": [
                        148.17018301458677,
                        151.3610258022691
                    ],
                    "time_duration": 3.190842787682328
                },
                {
                    "line": "just a-wishing",
                    "time_index": [
                        154.6531651863858,
                        156.17261413290117
                    ],
                    "time_duration": 1.5194489465153822
                },
                {
                    "line": "i'd stayed a little longer,",
                    "time_index": [
                        156.32455902755274,
                        159.46475351701787
                    ],
                    "time_duration": 3.140194489465131
                },
                {
                    "line": "oh, lord,",
                    "time_index": [
                        161.23744395461918,
                        162.30105821717996
                    ],
                    "time_duration": 1.063614262560776
                },
                {
                    "line": "let me tell you that the",
                    "time_index": [
                        162.80754119935176,
                        163.4659690761751
                    ],
                    "time_duration": 0.6584278768233389
                },
                {
                    "line": "feelings getting stronger.",
                    "time_index": [
                        163.56726567260947,
                        165.54254930307948
                    ],
                    "time_duration": 1.9752836304700168
                }
            ]
        },
        {
            "paragraph": "Verse",
            "occurrence": 3,
            "time_index": [
                169.34117166936795,
                193.90559630470023
            ],
            "time_duration": 24.564424635332273,
            "singer": [
                "Tom Waits"
            ],
            "lines": [
                {
                    "line": "and my time went so quickly,",
                    "time_index": [
                        169.34117166936795,
                        172.4813661588331
                    ],
                    "time_duration": 3.1401944894651592
                },
                {
                    "line": "i went lickety-splickly",
                    "time_index": [
                        172.63331105348465,
                        175.0644293679093
                    ],
                    "time_duration": 2.4311183144246513
                },
                {
                    "line": "out to my old 'fifty fife",
                    "time_index": [
                        176.63452661264188,
                        180.331852382496
                    ],
                    "time_duration": 3.6973257698541317
                },
                {
                    "line": "as i pulled away slowly,",
                    "time_index": [
                        182.45908090761756,
                        185.54862709886555
                    ],
                    "time_duration": 3.0895461912479902
                },
                {
                    "line": "feeling so holy,",
                    "time_index": [
                        186.4602964667748,
                        188.84076648298225
                    ],
                    "time_duration": 2.380470016207454
                },
                {
                    "line": "god knows,",
                    "time_index": [
                        188.94206307941658,
                        190.25891883306326
                    ],
                    "time_duration": 1.3168557536466778
                },
                {
                    "line": "i was feeling alive.",
                    "time_index": [
                        190.76540181523507,
                        193.90559630470023
                    ],
                    "time_duration": 3.1401944894651592
                }
            ]
        },
        {
            "paragraph": "Chorus",
            "occurrence": 3,
            "time_index": [
                195.27310035656407,
                226.32050716369537
            ],
            "time_duration": 31.047406807131296,
            "singer": [
                "Tom Waits"
            ],
            "lines": [
                {
                    "line": "and now the suns coming up,",
                    "time_index": [
                        195.27310035656407,
                        199.93274379254464
                    ],
                    "time_duration": 4.65964343598057
                },
                {
                    "line": "i'm riding with lady luck,",
                    "time_index": [
                        202.61710359805517,
                        206.41572596434366
                    ],
                    "time_duration": 3.798622366288498
                },
                {
                    "line": "freeway cars and trucks,",
                    "time_index": [
                        209.50527215559165,
                        213.10130132901142
                    ],
                    "time_duration": 3.5960291734197654
                },
                {
                    "line": "freeway cars and trucks,",
                    "time_index": [
                        216.1401992220422,
                        219.6855800972448
                    ],
                    "time_duration": 3.5453808752025964
                },
                {
                    "line": "freeway cars and trucks",
                    "time_index": [
                        222.7244779902756,
                        226.32050716369537
                    ],
                    "time_duration": 3.5960291734197654
                }
            ]
        }
    ]
}