{
    "meta": {
        "song_id": "00000761",
        "title": "Son Of My Father",
        "artist": "Chicory Tip",
        "language": "en"
    },
    "annotations": [
        {
            "paragraph": "Verse",
            "occurrence": 1,
            "time_index": [
                24.064,
                51.298990381694836
            ],
            "time_duration": 27.234990381694836,
            "singer": [
                "Chicory Tip"
            ],
            "lines": [
                {
                    "line": "mama said to me",
                    "time_index": [
                        24.064,
                        25.228321150146805
                    ],
                    "time_duration": 1.1643211501468045
                },
                {
                    "line": "we gotta have your life run right",
                    "time_index": [
                        25.27894380884884,
                        29.32875650501164
                    ],
                    "time_duration": 4.0498126961628
                },
                {
                    "line": "off you go to school",
                    "time_index": [
                        31.50553082919915,
                        32.66985197934595
                    ],
                    "time_duration": 1.164321150146801
                },
                {
                    "line": "where you can learn the rules there right",
                    "time_index": [
                        32.72047463804799,
                        35.96032479497823
                    ],
                    "time_duration": 3.2398501569302383
                },
                {
                    "line": "be just like your dabbling father",
                    "time_index": [
                        39.04830697580236,
                        41.275703958691906
                    ],
                    "time_duration": 2.2273969828895446
                },
                {
                    "line": "when it seems tradition",
                    "time_index": [
                        41.37694927609598,
                        44.566176774324184
                    ],
                    "time_duration": 3.189227498228206
                },
                {
                    "line": "never go as tray and stay an honest loving son",
                    "time_index": [
                        46.38859248759744,
                        51.298990381694836
                    ],
                    "time_duration": 4.910397894097393
                }
            ]
        },
        {
            "paragraph": "Chorus",
            "occurrence": 1,
            "time_index": [
                53.72887799939252,
                182.6647897134757
            ],
            "time_duration": 128.93591171408318,
            "singer": [
                "Chicory Tip"
            ],
            "lines": [
                {
                    "line": "son of my father",
                    "time_index": [
                        53.72887799939252,
                        56.41187891060038
                    ],
                    "time_duration": 2.6830009112078557
                },
                {
                    "line": "moulded i was folded i was free from draft",
                    "time_index": [
                        57.525577402045144,
                        60.91729553508149
                    ],
                    "time_duration": 3.391718133036349
                },
                {
                    "line": "son of my father",
                    "time_index": [
                        61.119786169889636,
                        63.80278708109749
                    ],
                    "time_duration": 2.6830009112078557
                },
                {
                    "line": "commanded i was branded in a plastic vac",
                    "time_index": [
                        64.71399493773413,
                        68.10571307077046
                    ],
                    "time_duration": 3.391718133036335
                },
                {
                    "line": "surrounded and confounded by statistic facts",
                    "time_index": [
                        68.40944902298267,
                        71.90241247342308
                    ],
                    "time_duration": 3.4929634504404135
                },
                {
                    "line": "tried to get me in",
                    "time_index": [
                        119.03210772501768,
                        120.24705153386654
                    ],
                    "time_duration": 1.214943808848858
                },
                {
                    "line": "but i jumped out of my skin in time",
                    "time_index": [
                        120.29767419256856,
                        124.09437359522119
                    ],
                    "time_duration": 3.796699402652621
                },
                {
                    "line": "i saw through their lies",
                    "time_index": [
                        126.47363855421685,
                        127.63795970436365
                    ],
                    "time_duration": 1.1643211501468045
                },
                {
                    "line": "and read the ali bi signs",
                    "time_index": [
                        127.84045033917178,
                        130.4728285916776
                    ],
                    "time_duration": 2.6323782525058164
                },
                {
                    "line": "so i left my home",
                    "time_index": [
                        133.71267874860786,
                        134.9276225574567
                    ],
                    "time_duration": 1.2149438088488296
                },
                {
                    "line": "i'm really on my own at last",
                    "time_index": [
                        135.0794905335628,
                        139.1293032297256
                    ],
                    "time_duration": 4.049812696162803
                },
                {
                    "line": "left the wrong path",
                    "time_index": [
                        140.95171894299887,
                        142.06541743444362
                    ],
                    "time_duration": 1.113698491444751
                },
                {
                    "line": "and separated from the past",
                    "time_index": [
                        142.26790806925177,
                        145.7608715196922
                    ],
                    "time_duration": 3.4929634504404135
                },
                {
                    "line": "son of my father",
                    "time_index": [
                        148.19075913738988,
                        150.62064675508753
                    ],
                    "time_duration": 2.429887617697659
                },
                {
                    "line": "changing rear ranging into some one new",
                    "time_index": [
                        151.9874585400425,
                        155.12606337956865
                    ],
                    "time_duration": 3.1386048395261525
                },
                {
                    "line": "son of my father",
                    "time_index": [
                        155.632289966589,
                        158.06217758428667
                    ],
                    "time_duration": 2.429887617697659
                },
                {
                    "line": "collecting and selecting independent views",
                    "time_index": [
                        159.12525341702943,
                        162.71946218487392
                    ],
                    "time_duration": 3.594208767844492
                },
                {
                    "line": "knowing and i'm showing how the change is due",
                    "time_index": [
                        162.92195281968205,
                        166.06055765920823
                    ],
                    "time_duration": 3.138604839526181
                },
                {
                    "line": "son of my father",
                    "time_index": [
                        168.38919995950184,
                        170.86971023590155
                    ],
                    "time_duration": 2.4805102763997127
                },
                {
                    "line": "moulded i was folded i was free from draft",
                    "time_index": [
                        172.08465404475038,
                        175.4257495190847
                    ],
                    "time_duration": 3.3410954743343098
                },
                {
                    "line": "son of my father",
                    "time_index": [
                        175.62824015389285,
                        178.2099957476966
                    ],
                    "time_duration": 2.581755593803763
                },
                {
                    "line": "commanded i was branded in a plastic vac",
                    "time_index": [
                        179.2224489217373,
                        182.6647897134757
                    ],
                    "time_duration": 3.4423407917383884
                }
            ]
        }
    ]
}