{
    "meta": {
        "song_id": "00000828",
        "title": "Perfect Situation",
        "artist": "Weezer",
        "language": "en"
    },
    "annotations": [
        {
            "paragraph": "Verse",
            "occurrence": 1,
            "time_index": [
                40.65,
                80.38436106510383
            ],
            "time_duration": 39.73436106510383,
            "singer": [
                "Weezer"
            ],
            "lines": [
                {
                    "line": "what's the deal with my brain?",
                    "time_index": [
                        40.65,
                        42.6805134412027
                    ],
                    "time_duration": 2.0305134412027
                },
                {
                    "line": "why am i so obviously insane?",
                    "time_index": [
                        43.19809529876417,
                        45.507306663269205
                    ],
                    "time_duration": 2.309211364505032
                },
                {
                    "line": "in a perfect situation",
                    "time_index": [
                        45.98507453178749,
                        48.214657918206136
                    ],
                    "time_duration": 2.2295833864186463
                },
                {
                    "line": "i lead love down the drain",
                    "time_index": [
                        48.81186775385399,
                        50.48405529366798
                    ],
                    "time_duration": 1.67218753981399
                },
                {
                    "line": "there's the pitch slow and straight",
                    "time_index": [
                        50.84238119505669,
                        53.07196458147534
                    ],
                    "time_duration": 2.2295833864186534
                },
                {
                    "line": "all i have to do is swing and i'm a hero",
                    "time_index": [
                        53.39047649382086,
                        57.21261944196712
                    ],
                    "time_duration": 3.822142948146258
                },
                {
                    "line": "but i'm a zero",
                    "time_index": [
                        58.44685310230602,
                        59.7607147407313
                    ],
                    "time_duration": 1.31386163842528
                },
                {
                    "line": "hungry nights once again",
                    "time_index": [
                        61.034762390113386,
                        63.105089820359275
                    ],
                    "time_duration": 2.0703274302458894
                },
                {
                    "line": "now it's getting unbelievable",
                    "time_index": [
                        63.58285768887755,
                        65.73281309720983
                    ],
                    "time_duration": 2.149955408332275
                },
                {
                    "line": "cause i could not have it better",
                    "time_index": [
                        66.29020894381449,
                        68.51979233023314
                    ],
                    "time_duration": 2.2295833864186534
                },
                {
                    "line": "but i just can't get no play",
                    "time_index": [
                        68.95774620970823,
                        70.86881768378137
                    ],
                    "time_duration": 1.9110714740731396
                },
                {
                    "line": "from the girls all around",
                    "time_index": [
                        71.22714358517008,
                        73.41691298254554
                    ],
                    "time_duration": 2.189769397375457
                },
                {
                    "line": "as they search the night",
                    "time_index": [
                        73.77523888393425,
                        75.16872850044591
                    ],
                    "time_duration": 1.3934896165116584
                },
                {
                    "line": "for someone to hold onto",
                    "time_index": [
                        75.28817046757547,
                        77.59738183208052
                    ],
                    "time_duration": 2.309211364505046
                },
                {
                    "line": "and just pass through",
                    "time_index": [
                        79.03068543763536,
                        80.38436106510383
                    ],
                    "time_duration": 1.3536756274684763
                }
            ]
        },
        {
            "paragraph": "Chorus",
            "occurrence": 1,
            "time_index": [
                81.41952478022677,
                96.94698050707095
            ],
            "time_duration": 15.527455726844181,
            "singer": [
                "Weezer"
            ],
            "lines": [
                {
                    "line": "singing",
                    "time_index": [
                        81.41952478022677,
                        81.97692062683143
                    ],
                    "time_duration": 0.5573958466046633
                },
                {
                    "line": "oh oh oh oh",
                    "time_index": [
                        82.13617658300419,
                        86.75459931201425
                    ],
                    "time_duration": 4.618422729010064
                },
                {
                    "line": "oh oh woah",
                    "time_index": [
                        87.15273920244616,
                        91.01469613963562
                    ],
                    "time_duration": 3.8619569371894613
                },
                {
                    "line": "singing",
                    "time_index": [
                        91.61190597528346,
                        92.16930182188813
                    ],
                    "time_duration": 0.5573958466046633
                },
                {
                    "line": "oh oh oh oh",
                    "time_index": [
                        92.32855777806088,
                        96.94698050707095
                    ],
                    "time_duration": 4.618422729010064
                },
                {
                    "line": "oh oh woah",
                    "time_index": [
                        97.34512039750285,
                        101.20707733469231
                    ],
                    "time_duration": 3.8619569371894613
                }
            ]
        },
        {
            "paragraph": "Verse",
            "occurrence": 2,
            "time_index": [
                101.80428717034016,
                121.1936998343738
            ],
            "time_duration": 19.389412664033642,
            "singer": [
                "Weezer"
            ],
            "lines": [
                {
                    "line": "get your hands off the girl",
                    "time_index": [
                        101.80428717034016,
                        103.91442858962924
                    ],
                    "time_duration": 2.1101414192890786
                },
                {
                    "line": "can't you see that she belongs to me?",
                    "time_index": [
                        104.35238246910433,
                        106.86066377882531
                    ],
                    "time_duration": 2.508281309720985
                },
                {
                    "line": "and i don't appreciate this",
                    "time_index": [
                        107.17917569117083,
                        109.44857306663269
                    ],
                    "time_duration": 2.269397375461864
                },
                {
                    "line": "excess company",
                    "time_index": [
                        110.24485284749647,
                        111.63834246400813
                    ],
                    "time_duration": 1.3934896165116584
                },
                {
                    "line": "though i can't satisfy",
                    "time_index": [
                        112.11611033252643,
                        114.22625175181551
                    ],
                    "time_duration": 2.1101414192890786
                },
                {
                    "line": "all the needs she has",
                    "time_index": [
                        114.54476366416102,
                        116.01788125875908
                    ],
                    "time_duration": 1.473117594598051
                },
                {
                    "line": "and so she starts to wander",
                    "time_index": [
                        116.13732322588862,
                        118.28727863422091
                    ],
                    "time_duration": 2.149955408332289
                },
                {
                    "line": "can you blame her?",
                    "time_index": [
                        119.91965218499169,
                        121.1936998343738
                    ],
                    "time_duration": 1.274047649382112
                }
            ]
        },
        {
            "paragraph": "Chorus",
            "occurrence": 2,
            "time_index": [
                122.22886354949674,
                137.75631927634092
            ],
            "time_duration": 15.527455726844181,
            "singer": [
                "Weezer"
            ],
            "lines": [
                {
                    "line": "singing",
                    "time_index": [
                        122.22886354949674,
                        122.82607338514458
                    ],
                    "time_duration": 0.5972098356478455
                },
                {
                    "line": "oh oh oh oh",
                    "time_index": [
                        122.94551535227416,
                        127.56393808128422
                    ],
                    "time_duration": 4.618422729010064
                },
                {
                    "line": "oh oh woah",
                    "time_index": [
                        127.96207797171613,
                        131.82403490890556
                    ],
                    "time_duration": 3.861956937189433
                },
                {
                    "line": "singing",
                    "time_index": [
                        132.42124474455343,
                        133.01845458020128
                    ],
                    "time_duration": 0.5972098356478455
                },
                {
                    "line": "oh oh oh oh",
                    "time_index": [
                        133.13789654733085,
                        137.75631927634092
                    ],
                    "time_duration": 4.618422729010064
                },
                {
                    "line": "oh oh woah",
                    "time_index": [
                        138.15445916677282,
                        142.01641610396226
                    ],
                    "time_duration": 3.861956937189433
                }
            ]
        },
        {
            "paragraph": "Bridge",
            "occurrence": 1,
            "time_index": [
                144.0071155561218,
                163.67522614345773
            ],
            "time_duration": 19.668110587335946,
            "singer": [
                "Weezer"
            ],
            "lines": [
                {
                    "line": "tell me there's a logic out there",
                    "time_index": [
                        144.0071155561218,
                        146.11725697541087
                    ],
                    "time_duration": 2.1101414192890786
                },
                {
                    "line": "leading me to better prepare",
                    "time_index": [
                        146.55521085488596,
                        148.66535227417504
                    ],
                    "time_duration": 2.1101414192890786
                },
                {
                    "line": "for the day that something really special might come",
                    "time_index": [
                        149.10330615365012,
                        152.92544910179637
                    ],
                    "time_duration": 3.8221429481462508
                },
                {
                    "line": "tell me there's some hope for me",
                    "time_index": [
                        154.19949675117846,
                        156.190196203338
                    ],
                    "time_duration": 1.9906994521595323
                },
                {
                    "line": "i don't wanna be lonely",
                    "time_index": [
                        156.82722002802902,
                        158.73829150210216
                    ],
                    "time_duration": 1.9110714740731396
                },
                {
                    "line": "for the rest of my days on the earth",
                    "time_index": [
                        159.45494330487958,
                        162.40117849407565
                    ],
                    "time_duration": 2.9462351891960736
                },
                {
                    "line": "oh",
                    "time_index": [
                        162.95857434068031,
                        163.67522614345773
                    ],
                    "time_duration": 0.7166518027774202
                }
            ]
        },
        {
            "paragraph": "Chorus",
            "occurrence": 3,
            "time_index": [
                184.49794241304622,
                204.60400687985728
            ],
            "time_duration": 20.106064466811063,
            "singer": [
                "Weezer"
            ],
            "lines": [
                {
                    "line": "oh oh oh oh",
                    "time_index": [
                        184.49794241304622,
                        189.11636514205628
                    ],
                    "time_duration": 4.618422729010064
                },
                {
                    "line": "oh oh woah",
                    "time_index": [
                        189.5145050324882,
                        193.37646196967765
                    ],
                    "time_duration": 3.8619569371894613
                },
                {
                    "line": "singing",
                    "time_index": [
                        193.9736718053255,
                        194.57088164097334
                    ],
                    "time_duration": 0.5972098356478455
                },
                {
                    "line": "oh oh oh oh",
                    "time_index": [
                        194.69032360810291,
                        199.30874633711298
                    ],
                    "time_duration": 4.618422729010064
                },
                {
                    "line": "oh oh woah",
                    "time_index": [
                        199.5874442604153,
                        203.44940119760477
                    ],
                    "time_duration": 3.8619569371894613
                },
                {
                    "line": "singing",
                    "time_index": [
                        204.04661103325262,
                        204.60400687985728
                    ],
                    "time_duration": 0.5573958466046633
                },
                {
                    "line": "oh woah",
                    "time_index": [
                        204.8827048031596,
                        213.0843865460568
                    ],
                    "time_duration": 8.201681742897193
                },
                {
                    "line": "woah",
                    "time_index": [
                        213.48252643648868,
                        223.2369537520703
                    ],
                    "time_duration": 9.754427315581609
                },
                {
                    "line": "woah",
                    "time_index": [
                        223.67490763154538,
                        225.78504905083446
                    ],
                    "time_duration": 2.1101414192890786
                },
                {
                    "line": "woah",
                    "time_index": [
                        226.22300293030958,
                        228.33314434959865
                    ],
                    "time_duration": 2.1101414192890786
                },
                {
                    "line": "woah",
                    "time_index": [
                        228.77109822907374,
                        230.88123964836282
                    ],
                    "time_duration": 2.1101414192890786
                },
                {
                    "line": "woah",
                    "time_index": [
                        231.3191935278379,
                        233.429334947127
                    ],
                    "time_duration": 2.1101414192890786
                },
                {
                    "line": "woah",
                    "time_index": [
                        233.86728882660208,
                        235.97743024589116
                    ],
                    "time_duration": 2.1101414192890786
                },
                {
                    "line": "woah",
                    "time_index": [
                        236.37557013632306,
                        238.48571155561214
                    ],
                    "time_duration": 2.1101414192890786
                },
                {
                    "line": "woah",
                    "time_index": [
                        238.96347942413044,
                        241.07362084341952
                    ],
                    "time_duration": 2.1101414192890786
                },
                {
                    "line": "woah",
                    "time_index": [
                        241.47176073385143,
                        243.5819021531405
                    ],
                    "time_duration": 2.1101414192890786
                },
                {
                    "line": "woah",
                    "time_index": [
                        244.05967002165877,
                        246.44850936425019
                    ],
                    "time_duration": 2.3888393425914103
                }
            ]
        }
    ]
}